string2date/__init__.py
string2date/string2date.py
harrytsz00-0.0.2.dist-info/LICENSE.txt
harrytsz00-0.0.2.dist-info/METADATA
harrytsz00-0.0.2.dist-info/WHEEL
harrytsz00-0.0.2.dist-info/top_level.txt
harrytsz00-0.0.2.dist-info/RECORD
