Metadata-Version: 2.1
Name: harrytsz00
Version: 0.0.2
Summary: string to date
Home-page: https://github.com/BigDataFounder/string2date
Author: harrytsz
Author-email: taosizhan@gmail.com
License: MIT
Platform: UNKNOWN
